rlabs_mini_box/__init__.py
rlabs_mini_box/config.py
rlabs_mini_box/data.py
rlabs_mini_box/directory.py
rlabs_mini_box/error.py
rlabs_mini_box/logger.py
rlabs_mini_box/manual_test_run.py
rlabs_mini_box/operations/__init__.py
rlabs_mini_box/operations/filter.py
rlabs_mini_box/operations/from_json.py
rlabs_mini_box/operations/index.py
rlabs_mini_box/operations/key.py
rlabs_mini_box/operations/map.py
rlabs_mini_box/operations/range.py
rlabs_mini_box/operations/select.py
rlabs_mini_box/operations/to_json.py
rlabs_mini_box/py.typed
rlabs_mini_box-1.0.4.dist-info/METADATA
rlabs_mini_box-1.0.4.dist-info/WHEEL
rlabs_mini_box-1.0.4.dist-info/entry_points.txt
rlabs_mini_box-1.0.4.dist-info/RECORD
